mtbp3cd/__init__.py
mtbp3cd/data/__init__.py
mtbp3cd/gui/__init__.py
mtbp3cd/gui/appclinicaldata.py
mtbp3cd/gui/appfileinventory.py
mtbp3cd/gui/gt01o_checksum.py
mtbp3cd/gui/gt01o_record.py
mtbp3cd/gui/gt01r_inputfolder.py
mtbp3cd/gui/gt01r_starting.py
mtbp3cd/gui/gt03o_adsl.py
mtbp3cd/gui/gt03o_define.py
mtbp3cd/gui/gt03r_inputfolder.py
mtbp3cd/util/__init__.py
mtbp3cd/util/gt03define.py
mtbp3cd/util/gt03plot.py
mtbp3cd/util/gt03summary.py
mtbp3cd/util/lsr.py
mtbp3cd/util/ltr.py
mtbp3cd-0.1.66.dist-info/METADATA
mtbp3cd-0.1.66.dist-info/WHEEL
mtbp3cd-0.1.66.dist-info/licenses/LICENSE
mtbp3cd-0.1.66.dist-info/RECORD
