Metadata-Version: 2.4
Name: mtbp3cd
Version: 0.1.66
Summary: my tool box for file management
License: GNU General Public License v3.0
License-File: LICENSE
Author: Y. Hsu
Requires-Python: >=3.10,<4.0
Classifier: License :: Other/Proprietary License
Classifier: Programming Language :: Python :: 3
Classifier: Programming Language :: Python :: 3.10
Classifier: Programming Language :: Python :: 3.11
Classifier: Programming Language :: Python :: 3.12
Classifier: Programming Language :: Python :: 3.13
Classifier: Programming Language :: Python :: 3.14
Provides-Extra: docs
Requires-Dist: pandas (>=2.0.0,<3.0.0)
Requires-Dist: seaborn (>=0.13.2,<0.14.0)
